LICENSE
README.md
setup.py
vexl/__init__.py
vexl/main.py
vexl.egg-info/PKG-INFO
vexl.egg-info/SOURCES.txt
vexl.egg-info/dependency_links.txt
vexl.egg-info/entry_points.txt
vexl.egg-info/top_level.txt